stream_valve/__init__.py
stream_valve/config.py
stream_valve/valve.py
stream_valve/version.py
stream_valve-0.1.0.dist-info/LICENSE
stream_valve-0.1.0.dist-info/METADATA
stream_valve-0.1.0.dist-info/WHEEL
stream_valve-0.1.0.dist-info/RECORD
