Metadata-Version: 2.1
Name: stream-valve
Version: 0.1.0
Summary: 
License: Apache-2.0 license
Author: Allen Chou
Author-email: f1470891079@gmail.com
Requires-Python: >=3.7.0,<4.0.0
Classifier: License :: Other/Proprietary License
Classifier: Programming Language :: Python :: 3
Classifier: Programming Language :: Python :: 3.7
Classifier: Programming Language :: Python :: 3.8
Classifier: Programming Language :: Python :: 3.9
Classifier: Programming Language :: Python :: 3.10
Classifier: Programming Language :: Python :: 3.11
Requires-Dist: pytz
Requires-Dist: rich
